<templateSet group="Java">
  <template name="tdd" value="@Test&#10;@DisplayName(&quot;&quot;)&#10;public void $name$ () throws Exception {&#10;// given&#10;&#10;// when&#10;&#10;// then&#10;}" description="Test Code Template" toReformat="false" toShortenFQNames="true">
    <variable name="name" expression="" defaultValue="" alwaysStopAt="true" />
    <context>
      <option name="JAVA_CODE" value="true" />
    </context>
  </template>
  <template name="test" value="// given&#10;&#10;// when&#10;&#10;// then" description="Test Template(Given, When, Then)" toReformat="false" toShortenFQNames="true">
    <context>
      <option name="JAVA_CODE" value="true" />
    </context>
  </template>
</templateSet>